doppler_pdm/__init__.py
doppler_pdm/run.py
doppler_pdm-1.0.2.dist-info/entry_points.txt
doppler_pdm-1.0.2.dist-info/WHEEL
doppler_pdm-1.0.2.dist-info/METADATA
doppler_pdm-1.0.2.dist-info/RECORD
